totango/__init__.py
totango_divvy-0.3.5.dist-info/AUTHORS.rst
totango_divvy-0.3.5.dist-info/LICENSE
totango_divvy-0.3.5.dist-info/METADATA
totango_divvy-0.3.5.dist-info/WHEEL
totango_divvy-0.3.5.dist-info/top_level.txt
totango_divvy-0.3.5.dist-info/RECORD
